atsphinx/og_article/__init__.py
atsphinx/og_article/models.py
atsphinx/og_article/processors.py
atsphinx_og_article-0.2.1.dist-info/LICENSE
atsphinx_og_article-0.2.1.dist-info/WHEEL
atsphinx_og_article-0.2.1.dist-info/METADATA
atsphinx_og_article-0.2.1.dist-info/RECORD
