Metadata-Version: 2.1
Name: atsphinx-og-article
Version: 0.2.1
Summary: Support article tpye's properties of Open Graph for Sphinx.
Author-email: Kazuya Takei <myself@attakei.net>
Classifier: Development Status :: 4 - Beta
Classifier: Framework :: Sphinx
Classifier: Framework :: Sphinx :: Extension
Classifier: Intended Audience :: Developers
Classifier: License :: OSI Approved :: Apache Software License
Classifier: Programming Language :: Python :: 3.8
Classifier: Programming Language :: Python :: 3.9
Classifier: Programming Language :: Python :: 3.10
Classifier: Programming Language :: Python :: 3.11
Classifier: Topic :: Documentation :: Sphinx
Requires-Dist: python-dateutil
Requires-Dist: sphinx
Requires-Dist: furo ; extra == "doc"
Requires-Dist: rst-pypi-ref ; extra == "doc"
Requires-Dist: sphinx ; extra == "doc"
Requires-Dist: beautifulsoup4 == 4.* ; extra == "test"
Requires-Dist: pytest ==7.* ; extra == "test"
Project-URL: Documentation, https://atsphinx-og-article.readthedocs.io/en/stable/
Project-URL: Source, https://github.com/atsphinx/og-article
Provides-Extra: doc
Provides-Extra: test
